{
  "forge_marker": 1,
  "defaults": {
    "model": "botania:pylon.obj",
    "transform": {
      "gui": {
        "rotation": [ {"x": 30}, {"y": 225}, {"z": 0} ],
        "translation": [ -0.25, 0, 0],
        "scale": 0.5625,
        "post-rotation": [ {"x": 0}, {"y": 0}, {"z": 0} ]
      },
      "ground": {
        "rotation": [ {"x": 0}, {"y": 0}, {"z": 0} ],
        "translation": [ 0, 0.1875, 0],
        "scale": 0.25,
        "post-rotation": [ {"x": 0}, {"y": 0}, {"z": 0} ]
      },
      "fixed": {
        "rotation": [ {"x": 0}, {"y": 0}, {"z": 0} ],
        "translation": [ 0, -0.15625, 0.3125 ],
        "scale": 0.5,
        "post-rotation": [ {"x": 0}, {"y": 0}, {"z": 0} ]
      },
      "thirdperson_righthand": {
        "rotation": [ {"x": 75}, {"y": 45}, {"z": 0} ],
        "translation": [ 0.125, -0.125, 0 ],
        "scale": 0.375,
        "post-rotation": [ {"x": 0}, {"y": 0}, {"z": 0} ]
      },
      "thirdperson_lefthand": {
        "rotation": [ {"x": 75}, {"y": 225}, {"z": 0} ],
        "translation": [ -0.375, 0.375, -0.125 ],
        "scale": 0.375,
        "post-rotation": [ {"x": 0}, {"y": 0}, {"z": 0} ]
      },
      "firstperson_righthand": {
        "rotation": [ {"x": 0}, {"y": 45}, {"z": 0} ],
        "translation": [ 0.375, 0, 0.25 ],
        "scale": 0.4,
        "post-rotation": [ {"x": 0}, {"y": 0}, {"z": 0} ]
      },
      "firstperson_lefthand": {
        "rotation": [ {"x": 0}, {"y": 225}, {"z": 0} ],
        "translation": [ -0.375, 0, -0.25 ],
        "scale": 0.4,
        "post-rotation": [ {"x": 0}, {"y": 0}, {"z": 0} ]
      }
    },
    "custom": {
      "flip-v": true
    }
  },
  "variants": {
    "variant": {
      "mana": { "textures": { "#pylon": "botania:model/pylon" } },
      "natura": { "textures": { "#pylon": "botania:model/pylon1" } },
      "gaia": { "textures": { "#pylon": "botania:model/pylon2" } }
    }
  }
}