{
  "type": "botania:petal_apothecary",
  "output": {
    "item": "botania:orechid"
  },
  "ingredients": [
    {
      "tag": "botania:petals/gray"
    },
    {
      "tag": "botania:petals/gray"
    },
    {
      "tag": "botania:petals/yellow"
    },
    {
      "tag": "botania:petals/yellow"
    },
    {
      "tag": "botania:petals/green"
    },
    {
      "tag": "botania:petals/green"
    },
    {
      "tag": "botania:petals/red"
    },
    {
      "tag": "botania:petals/red"
    }
  ]
}
