{
  "name": "botania.entry.missileRod",
  "category": "botania:tools",
  "icon": "botania:missile_rod",
  "entry_color": "aa00",
  "advancement": "botania:main/elf_lexicon_pickup",
  "pages": [
    {
      "type": "text",
      "text": {
        "translate": "botania.page.missileRod0"
      }
    },
    {
      "type": "text",
      "text": {
        "translate": "botania.page.missileRod2"
      }
    },
    {
      "type": "crafting",
      "text": {
        "translate": "botania.page.missileRod1"
      },
      "recipe": "botania:missile_rod"
    }
  ]
}
