{
  "parent": "minecraft:block/block",
  "textures": {
    "particle": "#side"
  },
  "elements": [
    {
      "name": "west",
      "from": [1, 1, 1],
      "to": [2, 15, 15],
      "faces": {
        "north": { "texture": "#side" },
        "east": { "texture": "#side" },
        "south": { "texture": "#side" },
        "west": { "texture": "#side" },
        "up": { "texture": "#front" }
      }
    },
    {
      "name": "east",
      "from": [14, 1, 1],
      "to": [15, 15, 15],
      "faces": {
        "north": { "texture": "#side" },
        "east": { "texture": "#side" },
        "south": { "texture": "#side" },
        "west": { "texture": "#side" },
        "up": { "texture": "#front" }
      }
    },
    {
      "name": "south",
      "from": [2, 1, 14],
      "to": [14, 15, 15],
      "faces": {
        "north": { "texture": "#side" },
        "south": { "texture": "#side" },
        "up": { "texture": "#front" }
      }
    },
    {
      "name": "north",
      "from": [2, 1, 1],
      "to": [14, 15, 2],
      "faces": {
        "north": { "texture": "#side" },
        "south": { "texture": "#side" },
        "up": { "texture": "#front" }
      }
    },
    {
      "name": "bottom",
      "from": [1, 1, 1],
      "to": [15, 2, 15],
      "faces": {
        "down": { "texture": "#back", "rotation": 180 }
      }
    }
  ]
}