{
  "parent": "minecraft:recipes/root",
  "rewards": {
    "recipes": [
      "botania:bifrost_pane"
    ]
  },
  "criteria": {
    "has_the_recipe": {
      "trigger": "minecraft:recipe_unlocked",
      "conditions": {
        "recipe": "botania:bifrost_pane"
      }
    },
    "has_required_item": {
      "trigger": "minecraft:inventory_changed",
      "conditions": {
        "items": [
          {
            "item": "botania:bifrost_perm"
          }
        ]
      }
    }
  },
  "requirements": [
    [
      "has_the_recipe",
      "has_required_item"
    ]
  ]
}